tamu_crossref/__init__.py
tamu_crossref/crossref/__init__.py
tamu_crossref/crossref/crossref.py
tamu_crossref/generate.py
tamu_crossref/lookup/__init__.py
tamu_crossref/lookup/lookup.py
tamu_crossref-0.1.1.dist-info/METADATA
tamu_crossref-0.1.1.dist-info/WHEEL
tamu_crossref-0.1.1.dist-info/entry_points.txt
tamu_crossref-0.1.1.dist-info/RECORD
